{
    "title": "Prólogo: El Regalo - El Velo Gravitacional (Audio-Libro Completo)",
    "voice": "es-DO-EmilioNeural",
    "background_music": "epic_intro_Bd1ucC7.mp3",
    "music_volume": 0.25,
    "blocks": [
        {
            "title": "Block 1: La Visión y el Despertar",
            "scenes": [
                {
                    "title": "El Sueño del Velo",
                    "text": "[TITLE]Prólogo: El Regalo[/TITLE] Ethan Ramírez despertó con el corazón martilleando contra las costillas, una sensación de vértigo que no pertenecía a su pequeña habitación en el Distrito RD. Acababa de salir de *ese* sueño otra vez. Esta vez, la visión había sido más nítida, casi tangible: se veía a sí mismo —o a alguien que usaba sus manos— dentro de una cabina de mando avanzada. A través de la placa frontal de un casco futurista, una red de datos y vectores parpadeaba en una interfaz [PHO:hache u de|HUD:h] que inundaba su campo de visión con luz cian. Frente a él, el espacio-tiempo se retorcía, colapsando en un túnel de geometría imposible, un agujero de gusano que rugía con un silencio absoluto mientras la nave se lanzaba hacia su centro. El latido de la máquina y el suyo propio eran una sola frecuencia. Sacudió la cabeza, tratando de atrapar la lógica de la visión, pero los fragmentos del casco y la cabina se le escapaban entre los dedos, dejando solo un rastro de inquietud fría en la nuca.",
                    "assets": [
                        {
                            "id": "ethan_vision_wormhole_edgerunners_fiel_1772396352741.png",
                            "zoom": "1.0:1.3",
                            "move": "HOR:50:50 + VER:0:50",
                            "shake": true,
                            "shake_intensity": 3,
                            "fit": false
                        }
                    ],
                    "sfx": [
                        {
                            "id": "heartbeat.mp3",
                            "volume": 0.6,
                            "offset": 0
                        },
                        {
                            "id": "rocket.mp3",
                            "volume": 0.4,
                            "offset": 2000
                        }
                    ]
                },
                {
                    "title": "Sabor a Calima",
                    "text": "Ethan se levantó con el sabor amargo y seco de la calima industrial pegado a la lengua. El aire del Distrito RD no era solo aire; era una suspensión pesada cargada de residuos de procesado y humedad ácida, donde la dispersión de Rayleigh se rendía ante una bruma permanente que convertía el sol en un disco amarillento, una pupila enferma que observaba desde el otro lado de la polución. Diecisiete años. Hoy cumplía diecisiete años, una cifra que en la periferia no se medía en pasteles ni deseos, sino en la capacidad de los pulmones para seguir filtrando el óxido de la existencia cotidiana.",
                    "assets": [
                        {
                            "id": "distrito_rd_edgerunners_fiel_v2_1772396386153.png",
                            "zoom": "1.2:1.0",
                            "move": "VER:100:0",
                            "overlay": "viento_polvo_de_estepa.mp4",
                            "fit": false
                        }
                    ]
                },
                {
                    "title": "El Domo de Goglee City",
                    "text": "Se incorporó en su pequeño catre, que chirrió con una frecuencia metálica y cansada. A través de la ventana rota, sellada con cinta de polímero que vibraba con un zumbido de baja frecuencia, el domo de [PHO:Gogle siti|Goglee City:h] brillaba a lo lejos con una pureza insultante. Era una semiesfera de cristal reforzado y campos de fuerza, una luna artificial que albergaba un mundo de presión atmosférica controlada y cielos de un azul espectral al que Ethan, por nacimiento y genética, nunca tendría invitación.",
                    "assets": [
                        {
                            "id": "goglee_dome_edgerunners_fiel_1772396405878.png",
                            "zoom": "1.0:1.2",
                            "move": "HOR:0:30",
                            "fit": false
                        }
                    ],
                    "sfx": [
                        {
                            "id": "cinematic_drone.mp3",
                            "volume": 0.3,
                            "offset": 0
                        }
                    ]
                }
            ]
        },
        {
            "title": "Block 2: El Taller",
            "scenes": [
                {
                    "title": "El Llamado de Carlos",
                    "text": "[EPICO]—¡Ethan! —La voz de Carlos, profunda y con la rugosidad de quien ha inhalado demasiado ozono de soldadura, retumbó desde el taller—. ¡Despierta, mijo! ¡Baja, que tengo algo que mostrarte![/EPICO]",
                    "assets": [
                        {
                            "id": "carlos_taller_edgerunners_fiel_1772396424909.png",
                            "zoom": "1.3:1.0",
                            "move": "HOR:50:60",
                            "fit": false
                        }
                    ]
                },
                {
                    "title": "Bajando al Taller",
                    "text": "Ethan se vistió con la eficiencia del hábito: la camiseta de tirantes gastada y los pantalones de carga manchados con lubricante sintético. Al bajar la escalera de metal, el calor del taller lo envolvió como un abrazo físico, trayendo consigo el aroma reconfortante del aceite de motor y el olor a tormenta de los sistemas de inducción.",
                    "assets": [
                        {
                            "id": "ethan_baja_escaleras.png",
                            "zoom": "1.1:1.0",
                            "move": "VER:100:0",
                            "fit": false
                        }
                    ]
                },
                {
                    "title": "Oasis de Entropía",
                    "text": "El taller de Carlos era un oasis de entropía organizada. Encajado entre estructuras condenadas del viejo mundo, era el único lugar donde Ethan sentía que la realidad se podía doblar si tenías las herramientas adecuadas. Su padre siempre lo decía: 'Una pieza de metal no está muerta mientras su resonancia sea pura'. Para Carlos Ramírez, los motores hablaban una lengua de vibraciones que Ethan empezaba a descifrar.",
                    "assets": [
                        {
                            "id": "carlos_taller_edgerunners_fiel_1772396424909.png",
                            "zoom": "1.0:1.2",
                            "move": "HOR:0:100",
                            "fit": false
                        }
                    ]
                },
                {
                    "title": "Descripción de Carlos",
                    "text": "Carlos lo esperaba junto al banco de trabajo. A sus cincuenta y seis años, sus manos eran un catálogo de la historia del Distrito: quemaduras por plasma, cicatrices de engranajes y piel curtida por el trabajo. Carlos era un hombre de lógica férrea y pragmatismo absoluto; para él, el universo no era más que una máquina vasta cuya única religión era el mantenimiento preventivo. Aunque repartía bendiciones por puro sedimento cultural caribeño, su verdadera fe residía en la precisión de un tornillo bien apretado. El taller estaba ahora vivo con el brillo azul de interfaces holográficas avanzadas que flotaban sobre las mesas de metal.",
                    "assets": [
                        {
                            "id": "carlos_taller_edgerunners_fiel_1772396424909.png",
                            "zoom": "1.1:1.3",
                            "move": "HOR:20:0",
                            "fit": false
                        }
                    ]
                }
            ]
        },
        {
            "title": "Block 3: La Moto",
            "scenes": [
                {
                    "title": "La Silueta bajo la Lona",
                    "text": "Detrás de él, bajo una lona de polímero que ocultaba su forma, se erguía una silueta aerodinámica, una promesa de movimiento. Algo que Ethan conocía bien por los rugidos de las carreras clandestinas del Distrito RD, pero que nunca había soñado con tocar.",
                    "assets": [
                        {
                            "id": "ethan_looking_at_gift.png",
                            "zoom": "1.0:1.2",
                            "move": "HOR:0:30",
                            "fit": false
                        }
                    ]
                },
                {
                    "title": "Cion Papi",
                    "text": "—Cion papi. Papi!... —Ethan se detuvo, sintiendo una fluctuación extraña en su ritmo cardíaco—. ¿Es lo que creo que es?",
                    "assets": [
                        {
                            "id": "ethan_looking_at_gift.png",
                            "zoom": "1.2:1.4",
                            "move": "HOR:50:50",
                            "fit": false
                        }
                    ]
                },
                {
                    "title": "Risa de Carlos",
                    "text": "[RISA]Carlos sonrió. —¡Jajaja! Dios te bendiga, mijo.[/RISA] —Por un segundo, el peso de la gravedad pareció aliviarse en sus hombros.",
                    "assets": [
                        {
                            "id": "carlos_hablando.png",
                            "zoom": "1.0:1.3",
                            "move": "HOR:50:50",
                            "fit": false
                        }
                    ]
                },
                {
                    "title": "El Núcleo Clase 3",
                    "text": "—Feliz cumple, mijo. No es una de esas máquinas de lujo con estabilizadores de neuronas que pilotan en la ciudad alta, pero tiene un núcleo de inducción Clase 3 que rescaté de los restos de un carguero. Es puro hierro, Ethan. [PHO:Latido puro|Latido:h] puro.",
                    "assets": [
                        {
                            "id": "carlos_hablando.png",
                            "zoom": "1.3:1.1",
                            "move": "HOR:30:50",
                            "fit": false
                        }
                    ]
                },
                {
                    "title": "Retirando la Lona",
                    "text": "Ethan se acercó como si temiera que la visión se desvaneciera. Al retirar la lona, el polvo bailó en la luz mortecina. El chasis estaba rayado y el asiento de cuero sintético tenía parches, pero bajo la carcasa de aleación, Ethan podía sentir el pulso de algo poderoso. Era el regalo más valioso que alguien en el Distrito RD podía recibir: un motor operativo, un par de alas de metal que aún no recordaban cómo volar.",
                    "assets": [
                        {
                            "id": "ethan_quitando_lona.png",
                            "zoom": "1.0:1.2",
                            "move": "HOR:50:60",
                            "overlay": "dust.mp4",
                            "fit": false
                        }
                    ],
                    "sfx": [
                        {
                            "id": "Power_Tool_Electrical_Buzz.mp3",
                            "volume": 0.4,
                            "offset": 1000
                        }
                    ]
                },
                {
                    "title": "Es Increíble",
                    "text": "—Es... es increíble, papi —susurró Ethan, pasando los dedos por el manillar. Notó la resistencia familiar de los controles, la firmeza de la horquilla—. El núcleo vibra... está viva.",
                    "assets": [
                        {
                            "id": "ethan_enciende_motowave.png",
                            "zoom": "1.0:1.2",
                            "move": "HOR:50:50",
                            "fit": false
                        }
                    ]
                },
                {
                    "title": "Es tu Proyecto",
                    "text": "—Está viva, mijo. La he estado armando por piezas estas últimas noches. El motor de combustión y el sistema de tracción por cadena están al cien; puedes rodarla por el asfalto del Distrito ahora mismo si quieres. Pero no levita todavía, Ethan. El sistema de fase está muerto y los propulsores gravitacionales son puro peso muerto por ahora. El resto... el resto lo vas a poner tú. Es tu proyecto ahora.",
                    "assets": [
                        {
                            "id": "ethan_enciende_motowave.png",
                            "zoom": "1.2:1.4",
                            "move": "HOR:50:50",
                            "fit": false
                        }
                    ]
                }
            ]
        },
        {
            "title": "Block 4: El Misterio",
            "scenes": [
                {
                    "title": "Anomalía de Datos",
                    "text": "Carlos suspiró, clavando la vista en un complejo [PHO:hologeama|holograma:h] que mostraba telemetría astronómica en tiempo real. Sus ojos, antes brillantes, se sombrearon por un instante. —Miro lo que otros ignoran, mijo. En el año 2100 vi un bamboleo de una estrella que no tenía sentido. Ahora, ese patrón se repite. Algo en estos datos no me gusta.",
                    "assets": [
                        {
                            "id": "carlos_viendo_telemetria_preocupado.png",
                            "zoom": "1.0:1.3",
                            "move": "HOR:50:30",
                            "fit": false
                        }
                    ]
                },
                {
                    "title": "Consejo de Piloto",
                    "text": "—Aprende a leer los vectores de escape si tanto te gustan las [PHO:mótoweivs|motowaves]. Los números no mienten, Ethan. En un vuelo crítico, lo único real es lo que marca el panel. No lo olvides.",
                    "assets": [
                        {
                            "id": "carlos_viendo_telemetria_preocupado.png",
                            "zoom": "1.3:1.1",
                            "move": "HOR:30:50",
                            "fit": false
                        }
                    ]
                },
                {
                    "title": "Memorias de Quisqueya",
                    "text": "Ethan cerró los ojos y, por un momento, las historias de Carlos cobraron vida. Historias de Quisqueya, la isla que el mar se tragó en 2065. Vio mares que no eran de petróleo, sino de un azul tan profundo que desafía la descripción, y cielos donde el sol no quemaba, sino que acariciaba. Ese legado era su única ancla en un mundo que quería hundirlo.",
                    "assets": [
                        {
                            "id": "media__1772308402329.jpg",
                            "zoom": "1.0:1.3",
                            "move": "HOR:50:50 + VER:0:100",
                            "fit": false,
                            "overlay": "rain.mp4"
                        }
                    ],
                    "sfx": [
                        {
                            "id": "ocean_waves.mp3",
                            "volume": 0.5,
                            "offset": 0
                        }
                    ]
                }
            ]
        },
        {
            "title": "Block 5: La Bendición",
            "scenes": [
                {
                    "title": "Hacia el Ritual",
                    "text": "Se giró hacia su padre, buscando el ritual que mantenía viva esa memoria.",
                    "assets": [
                        {
                            "id": "ethan_hablando.png",
                            "zoom": "1.0:1.2",
                            "move": "HOR:50:50",
                            "fit": false
                        }
                    ]
                },
                {
                    "title": "Ción Papi (Final)",
                    "text": "—Papi... Ción papi.",
                    "assets": [
                        {
                            "id": "ethan_hablando.png",
                            "zoom": "1.2:1.4",
                            "move": "HOR:50:50",
                            "fit": false
                        }
                    ]
                },
                {
                    "title": "Respeto Espiritual",
                    "text": "Ethan inclinó la cabeza con respeto. No era una simple costumbre; era una transferencia de momento espiritual, el reconocimiento de que su historia no empezaba con él, sino con los que cruzaron el mar cuando el mundo se rompió.",
                    "assets": [
                        {
                            "id": "carlos_blessing_fiel_fixed_1772416669581.png",
                            "zoom": "1.0:1.2",
                            "move": "HOR:50:50",
                            "fit": false
                        }
                    ]
                },
                {
                    "title": "Mano en el Hombro",
                    "text": "Carlos puso su mano callosa sobre el hombro de su hijo. El contacto fue cálido, una bendición grabada en el [PHO:adené|ADN:h] de su gente.",
                    "assets": [
                        {
                            "id": "carlos_blessing_fiel_fixed_1772416669581.png",
                            "zoom": "1.2:1.4",
                            "move": "HOR:50:50",
                            "fit": false
                        }
                    ]
                },
                {
                    "title": "La Única Verdad",
                    "text": "—Dios me lo bendiga y me lo haga un hombre de bien, mijo. Y nunca lo olvide: el conocimiento es la clave de todo, y en este mundo, la única verdad está en los datos. Aprenda a leerlos y nunca estará perdido.",
                    "assets": [
                        {
                            "id": "carlos_blessing_fiel_fixed_1772416669581.png",
                            "zoom": "1.4:1.1",
                            "move": "HOR:50:50",
                            "fit": false
                        }
                    ]
                }
            ]
        },
        {
            "title": "Block 6: El Fénix",
            "scenes": [
                {
                    "title": "Bautismo de Metal",
                    "text": "Ethan asintió, sintiendo que su masa corporal ya no era un lastre. Miró la [PHO:mótoweiv|motowave:h]. Ya tenía nombre en su mente, un nombre que evocaba el ciclo eterno de la materia. —La llamaré *El Fénix* —sentenció—. Porque vamos a quemar el aire del Distrito para salir volando de aquí.",
                    "assets": [
                        {
                            "id": "fenix_reveal_edgerunners_fiel_v2_1772396447054.png",
                            "zoom": "1.0:1.3",
                            "move": "HOR:100:0",
                            "fit": false
                        }
                    ],
                    "sfx": [
                        {
                            "id": "Sports_Car_Speeding.mp3",
                            "volume": 1.0,
                            "offset": 2000
                        }
                    ]
                },
                {
                    "title": "Orgullo y Sombra",
                    "text": "Carlos lo observó en silencio, con una mezcla de orgullo y una sombra de advertencia que Ethan aún no comprendía del todo. Darle la [PHO:mótoweiv|motowave:h] era darle un sueño, y en el Distrito RD, los sueños pesaban tanto como el plomo. Pero hoy, mientras Ethan sentía el pulso del motor bajo su palma, el universo entero parecía haber disminuido su constante gravitatoria solo para él.",
                    "assets": [
                        {
                            "id": "final_taller_shadow_png_1772311291464.png",
                            "zoom": "1.5:1.0",
                            "move": "HOR:50:50",
                            "fit": false
                        }
                    ]
                }
            ]
        }
    ]
}